hiq/__init__.py
hiq/base.py
hiq/constants.py
hiq/cv_torch.py
hiq/cv_torch_data.py
hiq/ddict.py
hiq/deterministic.py
hiq/distributed.py
hiq/hiq_utils.py
hiq/http_metric_client.py
hiq/jack.py
hiq/memory.py
hiq/model_params.py
hiq/monkeyking.py
hiq/node.py
hiq/node_utils.py
hiq/prometheus.py
hiq/server_flask.py
hiq/server_flask_with_oci_apm.py
hiq/tree.py
hiq/tree_func.py
hiq/tree_utils.py
hiq/utils.py
hiq/vendor_oci_apm.py
hiq/vendor_oci_streaming.py
hiq/vendor_oci_t2.py
hiq/vis.py
hiq/data/tau.pk
hiq/framework/__init__.py
hiq/framework/onnxruntime.py
hiq/framework/paddle.py
hiq/framework/paddleocr.conf
hiq/framework/paddleocr.py
hiq/framework/transformers.py
hiq/framework/fastapi/__init__.py
hiq/framework/fastapi/templates/hiq.html
hiq/framework/fastapi/templates/lat.html
hiq_python-1.1.14.dist-info/METADATA
hiq_python-1.1.14.dist-info/WHEEL
hiq_python-1.1.14.dist-info/top_level.txt
hiq_python-1.1.14.dist-info/RECORD
