Metadata-Version: 2.1
Name: hiq-python
Version: 1.1.14
Summary: HiQ - A Modern Observability System
Home-page: https://github.com/oracle/hiq
Author: Henry Fuheng Wu; Kathan Patel; Zixin Kong
Author-email: <fuheng.wu@oracle.com>
Keywords: hiq
Classifier: Programming Language :: Python :: 3
Classifier: Programming Language :: Python :: 3.8
Classifier: Programming Language :: Python :: 3.9
Classifier: Programming Language :: Python :: 3.10
Requires-Dist: PyYAML
Requires-Dist: cachetools
Requires-Dist: psutil
Requires-Dist: py-itree
Requires-Dist: urllib3
Requires-Dist: requests
Requires-Dist: rich
Provides-Extra: fastapi
Requires-Dist: fastapi ; extra == 'fastapi'
Requires-Dist: uvicorn ; extra == 'fastapi'
Requires-Dist: pandas ; extra == 'fastapi'
Provides-Extra: full
Requires-Dist: fastapi ; extra == 'full'
Requires-Dist: uvicorn ; extra == 'full'
Requires-Dist: pandas ; extra == 'full'
Requires-Dist: torch >=1.13.1 ; extra == 'full'
Requires-Dist: transformer >=4.26.1 ; extra == 'full'
Requires-Dist: protobuf ~=3.20.2 ; extra == 'full'
Requires-Dist: importlib-metadata >=6.0.0 ; extra == 'full'
Requires-Dist: salesforce-lavis ; extra == 'full'
Requires-Dist: pynvml ; extra == 'full'
Provides-Extra: gpu
Requires-Dist: pynvml ; extra == 'gpu'
Provides-Extra: lavis
Requires-Dist: salesforce-lavis ; extra == 'lavis'
Provides-Extra: transformers
Requires-Dist: torch >=1.13.1 ; extra == 'transformers'
Requires-Dist: transformer >=4.26.1 ; extra == 'transformers'
Requires-Dist: protobuf ~=3.20.2 ; extra == 'transformers'
Requires-Dist: importlib-metadata >=6.0.0 ; extra == 'transformers'
